happenings/__init__.py
happenings/admin.py
happenings/forms.py
happenings/how_to.md
happenings/models.py
happenings/signals.py
happenings/tests.py
happenings/urls.py
happenings/views.py
happenings/fixtures/auth_users.json
happenings/fixtures/events.json
happenings/static/happenings/events.css
happenings/static/happenings/jquery.hcal.js
happenings/static/libs/pickadate.css
happenings/templates/happenings/add_memories.html
happenings/templates/happenings/base.html
happenings/templates/happenings/event_comments.html
happenings/templates/happenings/event_detail.html
happenings/templates/happenings/event_extra.html
happenings/templates/happenings/event_form.html
happenings/templates/happenings/event_map.html
happenings/templates/happenings/event_slides.html
happenings/templates/happenings/index.html
happenings/templates/happenings/memory_detail.html
happenings/templates/happenings/memory_list.html
happenings/templates/happenings/attending/list.html
happenings/templates/happenings/includes/event_info.html
happenings/templates/happenings/includes/event_selects.html
happenings/templates/happenings/includes/event_subnav.html
happenings/templates/happenings/includes/latest_comments.html
happenings/templates/happenings/includes/latest_updates.html
happenings/templates/happenings/includes/map.js
happenings/templates/happenings/includes/past_events.html
happenings/templates/happenings/includes/widget.html
happenings/templates/happenings/test/get_events_by_date.html
happenings/templates/happenings/updates/update_detail.html
happenings/templates/happenings/updates/update_list.html
happenings/templates/happenings/updates/update_slides.html
happenings/templatetags/__init__.py
happenings/templatetags/event_tags.py
tango_happenings-0.15.0.dist-info/METADATA
tango_happenings-0.15.0.dist-info/RECORD
tango_happenings-0.15.0.dist-info/WHEEL
tango_happenings-0.15.0.dist-info/top_level.txt
