Metadata-Version: 1.1
Name: tango-happenings
Version: 0.15.0
Summary: Reusable Django events and calendaring.
Home-page: https://github.com/tBaxter/django-happenings
Author: Tim Baxter
Author-email: mail.baxter@gmail.com
License: MIT
Platform: UNKNOWN
Classifier: Development Status :: 4 - Beta
Classifier: Environment :: Web Environment
Classifier: Framework :: Django
Classifier: Intended Audience :: Developers
Classifier: License :: OSI Approved :: MIT License
Classifier: Programming Language :: Python
Classifier: Programming Language :: Python :: 3.4
Classifier: Programming Language :: Python :: 3.5
